.gitignore
README.md
a.py
ode.md
setup.py
docs/Makefile
docs/conf.py
docs/index.rst
docs/make.bat
docs/apis/ode.rst
docs/apis/sde.rst
examples/__init__.py
examples/ode/__init__.py
examples/ode/tests.py
integrators/__init__.py
integrators/profile.py
integrators/state.py
integrators.egg-info/PKG-INFO
integrators.egg-info/SOURCES.txt
integrators.egg-info/dependency_links.txt
integrators.egg-info/requires.txt
integrators.egg-info/top_level.txt
integrators/backend/__init__.py
integrators/delay_fde/__init__.py
integrators/delay_fde/abm_methods.py
integrators/ode/__init__.py
integrators/ode/adaptive_methods.py
integrators/ode/other_methods.py
integrators/ode/runge_kutta_methods.py
integrators/sde/__init__.py
integrators/sde/other_methods.py
integrators/sde/srk_scalar.py
integrators/sde/srk_strong.py
integrators/sde/srk_weak.py