Metadata-Version: 1.2
Name: integrators
Version: 0.1.1
Summary: Integrators: A backend-free numerical integration library for differential equations
Home-page: UNKNOWN
Author: Chaoming Wang
Author-email: adaduo@outlook.com
License: UNKNOWN
Keywords: computational-neuroscience differential-equations numerical-integration ordinary-differential-equations ODE stochastic-differential-equations SDEdelay-differential-equations DDEfractional-differential-equations FDE
Platform: UNKNOWN
Classifier: Intended Audience :: Science/Research
Classifier: License :: OSI Approved :: GNU General Public License v3 (GPLv3)
Classifier: Natural Language :: English
Classifier: Operating System :: OS Independent
Classifier: Programming Language :: Python
Classifier: Programming Language :: Python :: 3
Classifier: Programming Language :: Python :: 3.6
Classifier: Programming Language :: Python :: 3.7
Classifier: Programming Language :: Python :: 3.8
Classifier: Programming Language :: Python :: 3.9
Classifier: Topic :: Scientific/Engineering :: Bio-Informatics
Classifier: Topic :: Scientific/Engineering :: Mathematics
Classifier: Topic :: Scientific/Engineering :: Artificial Intelligence
Classifier: Topic :: Software Development :: Libraries
Requires-Python: >=3.6
